okx/__init__.py
okx/ccxt/__init__.py
okx/ccxt/okx.py
okx/ccxt/abstract/okx.py
okx/ccxt/async_support/__init__.py
okx/ccxt/async_support/okx.py
okx/ccxt/async_support/base/__init__.py
okx/ccxt/async_support/base/exchange.py
okx/ccxt/async_support/base/throttler.py
okx/ccxt/async_support/base/ws/__init__.py
okx/ccxt/async_support/base/ws/cache.py
okx/ccxt/async_support/base/ws/client.py
okx/ccxt/async_support/base/ws/functions.py
okx/ccxt/async_support/base/ws/future.py
okx/ccxt/async_support/base/ws/order_book.py
okx/ccxt/async_support/base/ws/order_book_side.py
okx/ccxt/base/__init__.py
okx/ccxt/base/decimal_to_precision.py
okx/ccxt/base/errors.py
okx/ccxt/base/exchange.py
okx/ccxt/base/precise.py
okx/ccxt/base/types.py
okx/ccxt/pro/__init__.py
okx/ccxt/pro/okx.py
okx/ccxt/static_dependencies/README.md
okx/ccxt/static_dependencies/__init__.py
okx/ccxt/static_dependencies/bip/__init__.py
okx/ccxt/static_dependencies/bip/addr/P2PKH_addr.py
okx/ccxt/static_dependencies/bip/addr/__init__.py
okx/ccxt/static_dependencies/bip/addr/addr_dec_utils.py
okx/ccxt/static_dependencies/bip/addr/addr_key_validator.py
okx/ccxt/static_dependencies/bip/addr/iaddr_decoder.py
okx/ccxt/static_dependencies/bip/addr/iaddr_encoder.py
okx/ccxt/static_dependencies/bip/base58/__init__.py
okx/ccxt/static_dependencies/bip/base58/base58.py
okx/ccxt/static_dependencies/bip/base58/base58_ex.py
okx/ccxt/static_dependencies/bip/base58/base58_xmr.py
okx/ccxt/static_dependencies/bip/bech32/__init__.py
okx/ccxt/static_dependencies/bip/bech32/bch_bech32.py
okx/ccxt/static_dependencies/bip/bech32/bech32.py
okx/ccxt/static_dependencies/bip/bech32/bech32_base.py
okx/ccxt/static_dependencies/bip/bech32/bech32_ex.py
okx/ccxt/static_dependencies/bip/bech32/segwit_bech32.py
okx/ccxt/static_dependencies/bip/bip32/__init__.py
okx/ccxt/static_dependencies/bip/bip32/bip32_const.py
okx/ccxt/static_dependencies/bip/bip32/bip32_ex.py
okx/ccxt/static_dependencies/bip/bip32/bip32_key_data.py
okx_exchange-0.0.121.dist-info/METADATA
okx_exchange-0.0.121.dist-info/WHEEL
okx_exchange-0.0.121.dist-info/RECORD
